LSFExtractor/Cube.py
LSFExtractor/Spectrum.py
LSFExtractor/__init__.py
LSFExtractor-0.0.1.data/scripts/Spectrum.py
LSFExtractor-0.0.1.dist-info/LICENCE.md
LSFExtractor-0.0.1.dist-info/METADATA
LSFExtractor-0.0.1.dist-info/WHEEL
LSFExtractor-0.0.1.dist-info/top_level.txt
LSFExtractor-0.0.1.dist-info/RECORD
