Metadata-Version: 2.1
Name: LSFExtractor
Version: 0.0.1
Summary: A Python module to estimate the Line Spread Function
License: MIT License
Classifier: Intended Audience :: Science/Research
Classifier: License :: OSI Approved :: MIT License
Classifier: Operating System :: OS Independent
Classifier: Development Status :: 4 - Beta
Classifier: Topic :: Scientific/Engineering :: Astronomy
Classifier: Natural Language :: English
Classifier: Programming Language :: Python
Classifier: Topic :: Software Development :: Libraries :: Python Modules
License-File: LICENCE.md
Requires-Dist: astropy ==6.1.1
Requires-Dist: astropy-iers-data ==0.2024.7.8.0.31.19
Requires-Dist: certifi ==2024.7.4
Requires-Dist: charset-normalizer ==3.3.2
Requires-Dist: colorama ==0.4.6
Requires-Dist: contourpy ==1.2.1
Requires-Dist: cycler ==0.12.1
Requires-Dist: docutils ==0.21.2
Requires-Dist: fonttools ==4.53.1
Requires-Dist: idna ==3.7
Requires-Dist: importlib-metadata ==8.0.0
Requires-Dist: jaraco.classes ==3.4.0
Requires-Dist: jaraco.context ==5.3.0
Requires-Dist: jaraco.functools ==4.0.1
Requires-Dist: keyring ==25.2.1
Requires-Dist: kiwisolver ==1.4.5
Requires-Dist: markdown-it-py ==3.0.0
Requires-Dist: matplotlib ==3.9.1
Requires-Dist: mdurl ==0.1.2
Requires-Dist: more-itertools ==10.3.0
Requires-Dist: nh3 ==0.2.18
Requires-Dist: numpy ==1.26.4
Requires-Dist: packaging ==24.1
Requires-Dist: pillow ==10.4.0
Requires-Dist: pkginfo ==1.10.0
Requires-Dist: pyerfa ==2.0.1.4
Requires-Dist: Pygments ==2.18.0
Requires-Dist: pyparsing ==3.1.2
Requires-Dist: python-dateutil ==2.9.0.post0
Requires-Dist: pywin32-ctypes ==0.2.2
Requires-Dist: PyYAML ==6.0.1
Requires-Dist: readme-renderer ==44.0
Requires-Dist: requests ==2.32.3
Requires-Dist: requests-toolbelt ==1.0.0
Requires-Dist: rfc3986 ==2.0.0
Requires-Dist: rich ==13.7.1
Requires-Dist: scipy ==1.14.0
Requires-Dist: setuptools ==70.3.0
Requires-Dist: six ==1.16.0
Requires-Dist: tqdm ==4.66.4
Requires-Dist: twine ==5.1.1
Requires-Dist: urllib3 ==2.2.2
Requires-Dist: wheel ==0.43.0
Requires-Dist: zipp ==3.19.2
